{"assets":{"BDFE54253E49BC2944034CE21FB345B7":{"type":"texture","index":0,"assetRequest":{"type":"slide","state":"contents","slide":"none"},"url":{"native":"assets\/309CE55A-AA76-46C2-A553-DC61C4D2AF78.pdf"},"width":1024,"height":768},"9D050263ED2FB1FD406661B06A3995E6":{"type":"texture","index":1,"assetRequest":{"type":"slide","state":"contents","slide":"none"},"url":{"native":"assets\/309CE55A-AA76-46C2-A553-DC61C4D2AF78.pdf"},"width":1024,"height":768}},"events":[{"effects":[{"beginTime":0,"baseLayer":{"animations":[],"initialState":{"affineTransform":[1,0,0,1,0,0],"masksToBounds":false,"rotation":0,"scale":1,"position":{"pointX":512,"pointY":384},"width":1024,"sublayerTransform":[1,0,0,0,0,1,0,0,0,0,1,0,0,0,0,1],"contentsRect":{"y":0,"x":0,"width":1,"height":1},"opacity":1,"edgeAntialiasingMask":251658240,"height":768,"hidden":false,"anchorPoint":{"pointX":0.5,"pointY":0.5}},"objectID":"0","layers":[{"animations":[],"initialState":{"affineTransform":[1,0,0,1,0,0],"masksToBounds":false,"rotation":0,"scale":1,"position":{"pointX":512,"pointY":384},"width":1024,"sublayerTransform":[1,0,0,0,0,1,0,0,0,0,1,-0.00049229876906403734,0,0,0,1],"contentsRect":{"y":0,"x":0,"width":1,"height":1},"opacity":1,"edgeAntialiasingMask":251658240,"height":768,"hidden":false,"anchorPoint":{"pointX":0.5,"pointY":0.5}},"layers":[{"animations":[],"layers":[],"texturedRectangle":{"isBackgroundTexture":false,"singleTextureOpacity":1,"textureType":0,"textBaseline":0,"textXHeight":0,"isVerticalText":false},"initialState":{"affineTransform":[1,0,0,1,0,0],"masksToBounds":false,"rotation":0,"scale":1,"position":{"pointX":512,"pointY":384},"width":1024,"sublayerTransform":[1,0,0,0,0,1,0,0,0,0,1,0,0,0,0,1],"contentsRect":{"y":0,"x":0,"width":1,"height":1},"opacity":1,"edgeAntialiasingMask":0,"height":768,"hidden":false,"anchorPoint":{"pointX":0.5,"pointY":0.5}},"texture":"9D050263ED2FB1FD406661B06A3995E6"},{"animations":[{"additive":false,"timeOffset":0,"beginTime":0,"from":{"scalar":false},"repeatCount":0,"fillMode":"both","duration":0.01,"autoreverses":false,"property":"hidden","to":{"scalar":true},"removedOnCompletion":false}],"layers":[],"texturedRectangle":{"isBackgroundTexture":false,"singleTextureOpacity":1,"textureType":0,"textBaseline":0,"textXHeight":0,"isVerticalText":false},"initialState":{"affineTransform":[1,0,0,1,0,0],"masksToBounds":false,"rotation":0,"scale":1,"position":{"pointX":512,"pointY":384},"width":1024,"sublayerTransform":[1,0,0,0,0,1,0,0,0,0,1,0,0,0,0,1],"contentsRect":{"y":0,"x":0,"width":1,"height":1},"opacity":1,"edgeAntialiasingMask":0,"height":768,"hidden":false,"anchorPoint":{"pointX":0.5,"pointY":0.5}},"texture":"BDFE54253E49BC2944034CE21FB345B7"}]}]},"effects":[],"duration":0.01,"type":"transition","attributes":{"direction":0},"name":"none","objectID":"0"}],"automaticPlay":false,"hyperlinks":[],"accessibility":[{"text":"￼","targetRectangle":{"y":715,"x":974.49816912412643,"width":13.34765625,"height":14}},{"text":"功能 2","targetRectangle":{"y":264.41693079471588,"x":803.79974365234375,"width":36.841796875,"height":21.600000858306885}},{"text":"功能 1","targetRectangle":{"y":264.41693079471588,"x":494.16751098632812,"width":36.841796875,"height":21.600000858306885}},{"text":"結合功能","targetRectangle":{"y":61.499999344348907,"x":375,"width":96,"height":33}},{"text":"現在你已經學到各種功能，接下來該看看什麼組合最適合你的 app 了。首先，發揮你的想像力，嘗試結合不同的功能。將所有功能寫在不同的紙上，然後將它們摺起來。每人輪流至少抽出兩張紙，並提出組合這些功能的方法。例如，你可以使用加速感應器和藍芽功能來連接一個機械人，並以你的裝置當作遙控器使用。","targetRectangle":{"y":104.76921081542969,"x":375,"width":588,"height":108.00000381469727}},{"text":"結合功能","targetRectangle":{"y":374.32568323612213,"x":642.21807861328125,"width":52,"height":21.600000858306885}},{"text":"規劃","targetRectangle":{"y":62,"x":43.15966796875,"width":60,"height":67}},{"text":"UI\/UX","targetRectangle":{"y":129,"x":43.15966796875,"width":58.673828125,"height":26}},{"text":"iOS 功能","targetRectangle":{"y":155,"x":43.15966796875,"width":88.0107421875,"height":30}},{"text":"基本功能","targetRectangle":{"y":185,"x":63.159668564796448,"width":68,"height":32.80000114440918}},{"text":"輕鬆連接","targetRectangle":{"y":217.80000114440918,"x":63.159668803215027,"width":68,"height":28.80000114440918}},{"text":"發揮創意","targetRectangle":{"y":246.60000228881836,"x":63.159668803215027,"width":68,"height":28.80000114440918}},{"text":"輔助使用","targetRectangle":{"y":275.40000343322754,"x":63.159668803215027,"width":68,"height":28.80000114440918}},{"text":"結合功能","targetRectangle":{"y":304.20000457763672,"x":63.159668803215027,"width":68,"height":28.80000114440918}},{"text":"設計","targetRectangle":{"y":333.0000057220459,"x":43.15966796875,"width":44,"height":30}}],"baseLayer":{"animations":[],"initialState":{"affineTransform":[1,0,0,1,0,0],"masksToBounds":false,"rotation":0,"scale":1,"position":{"pointX":512,"pointY":384},"width":1024,"sublayerTransform":[1,0,0,0,0,1,0,0,0,0,1,0,0,0,0,1],"contentsRect":{"y":0,"x":0,"width":1,"height":1},"opacity":1,"edgeAntialiasingMask":251658240,"height":768,"hidden":false,"anchorPoint":{"pointX":0.5,"pointY":0.5}},"objectID":"0","layers":[{"animations":[],"initialState":{"affineTransform":[1,0,0,1,0,0],"masksToBounds":false,"rotation":0,"scale":1,"position":{"pointX":512,"pointY":384},"width":1024,"sublayerTransform":[1,0,0,0,0,1,0,0,0,0,1,-0.00049229876906403734,0,0,0,1],"contentsRect":{"y":0,"x":0,"width":1,"height":1},"opacity":1,"edgeAntialiasingMask":251658240,"height":768,"hidden":false,"anchorPoint":{"pointX":0.5,"pointY":0.5}},"layers":[{"animations":[],"layers":[],"texturedRectangle":{"isBackgroundTexture":false,"singleTextureOpacity":1,"textureType":0,"textBaseline":0,"textXHeight":0,"isVerticalText":false},"initialState":{"affineTransform":[1,0,0,1,0,0],"masksToBounds":false,"rotation":0,"scale":1,"position":{"pointX":512,"pointY":384},"width":1024,"sublayerTransform":[1,0,0,0,0,1,0,0,0,0,1,0,0,0,0,1],"contentsRect":{"y":0,"x":0,"width":1,"height":1},"opacity":1,"edgeAntialiasingMask":0,"height":768,"hidden":false,"anchorPoint":{"pointX":0.5,"pointY":0.5}},"texture":"BDFE54253E49BC2944034CE21FB345B7"}]}]}}]}